dclassql/.gitignore
dclassql/__init__.py
dclassql/cli.py
dclassql/codegen.py
dclassql/db_pool.py
dclassql/model_inspector.py
dclassql/push/__init__.py
dclassql/push/base.py
dclassql/push/sqlite.py
dclassql/runtime/backends/__init__.py
dclassql/runtime/backends/base.py
dclassql/runtime/backends/lazy.py
dclassql/runtime/backends/metadata.py
dclassql/runtime/backends/protocols.py
dclassql/runtime/backends/sqlite.py
dclassql/runtime/backends/where_compiler.py
dclassql/runtime/datasource.py
dclassql/runtime/sqlite_adapters.py
dclassql/table_spec.py
dclassql/templates/__init__.py
dclassql/templates/client_module.py.jinja
dclassql/templates/partials/client_class.jinja
dclassql/templates/partials/exports.jinja
dclassql/templates/partials/imports.jinja
dclassql/templates/partials/macros.jinja
dclassql/templates/partials/model_section.jinja
dclassql/templates/partials/scalar_filters.jinja
dclassql/typing.py
dclassql/unwarp.py
dclassql/utils/__init__.py
dclassql/utils/ensure.py
dclassql-0.1.5.dist-info/WHEEL
dclassql-0.1.5.dist-info/entry_points.txt
dclassql-0.1.5.dist-info/METADATA
dclassql-0.1.5.dist-info/RECORD
