Metadata-Version: 2.3
Name: dclassql
Version: 0.1.5
Summary: A type-safe ORM generator for Python, creating fully type-hinted database clients from plain dataclass definitions.
Keywords: orm,codegen,sqlite,dataclass,typed
Author: myuanz
Author-email: myuanz <provefars@gmail.com>
License: MIT
Classifier: Programming Language :: Python :: 3.12
Classifier: Programming Language :: Python :: 3.13
Classifier: Programming Language :: Python :: 3.14
Classifier: License :: OSI Approved :: MIT License
Classifier: Intended Audience :: Developers
Classifier: Typing :: Typed
Requires-Dist: jinja2>=3.1.6
Requires-Dist: pypika>=0.48.9
Requires-Dist: typing-extensions>=4.12.2
Requires-Python: >=3.12
Project-URL: Homepage, https://github.com/myuanz/dataclassql
